pyaapalarmmodule/__init__.py
pyaapalarmmodule/aap_base_client.py
pyaapalarmmodule/alarm_panel.py
pyaapalarmmodule/crow_defs.py
pyaapalarmmodule/status_state.py
pyaapalarmmodule-2024.11.24.dist-info/LICENSE
pyaapalarmmodule-2024.11.24.dist-info/METADATA
pyaapalarmmodule-2024.11.24.dist-info/WHEEL
pyaapalarmmodule-2024.11.24.dist-info/top_level.txt
pyaapalarmmodule-2024.11.24.dist-info/RECORD
